pulumi_civo/__init__.py
pulumi_civo/_inputs.py
pulumi_civo/_utilities.py
pulumi_civo/database.py
pulumi_civo/dns_domain_name.py
pulumi_civo/dns_domain_record.py
pulumi_civo/firewall.py
pulumi_civo/get_database.py
pulumi_civo/get_database_version.py
pulumi_civo/get_disk_image.py
pulumi_civo/get_dns_domain_name.py
pulumi_civo/get_dns_domain_record.py
pulumi_civo/get_firewall.py
pulumi_civo/get_instance.py
pulumi_civo/get_instances.py
pulumi_civo/get_kubernetes_cluster.py
pulumi_civo/get_kubernetes_version.py
pulumi_civo/get_load_balancer.py
pulumi_civo/get_network.py
pulumi_civo/get_object_store.py
pulumi_civo/get_object_store_credential.py
pulumi_civo/get_region.py
pulumi_civo/get_reserved_ip.py
pulumi_civo/get_size.py
pulumi_civo/get_ssh_key.py
pulumi_civo/get_volume.py
pulumi_civo/instance.py
pulumi_civo/instance_reserved_ip_assignment.py
pulumi_civo/kubernetes_cluster.py
pulumi_civo/kubernetes_node_pool.py
pulumi_civo/network.py
pulumi_civo/object_store.py
pulumi_civo/object_store_credential.py
pulumi_civo/outputs.py
pulumi_civo/provider.py
pulumi_civo/pulumi-plugin.json
pulumi_civo/py.typed
pulumi_civo/reserved_ip.py
pulumi_civo/ssh_key.py
pulumi_civo/volume.py
pulumi_civo/volume_attachment.py
pulumi_civo/config/__init__.py
pulumi_civo/config/__init__.pyi
pulumi_civo/config/vars.py
pulumi_civo-2.4.8.dist-info/METADATA
pulumi_civo-2.4.8.dist-info/WHEEL
pulumi_civo-2.4.8.dist-info/top_level.txt
pulumi_civo-2.4.8.dist-info/RECORD
